{
  "permalink": "/question-man",
  "editUrl": "https://github.com/kuizuo/blog/edit/main/blog/project/题小侠.md",
  "source": "@site/blog/project/题小侠.md",
  "title": "题小侠",
  "description": "很早就了解与学习过微信小程序开发相关的技术栈与框架，小程序的账号也都已经申请过。但写过的 demo 项目也迟迟没有发布到小程序上。这主要的原因还是觉得不值得发布，加上各种审核相关的。而这次准备写一个搜题相关的小程序，也是时候实战发布一下，顺带记录下整个开发与发布过程。",
  "date": "2022-04-06T00:00:00.000Z",
  "formattedDate": "2022年4月6日",
  "tags": [
    {
      "label": "project",
      "permalink": "/tags/project"
    },
    {
      "label": "vue",
      "permalink": "/tags/vue"
    },
    {
      "label": "miniprogram",
      "permalink": "/tags/miniprogram"
    }
  ],
  "readingTime": 11.383333333333333,
  "hasTruncateMarker": true,
  "authors": [
    {
      "name": "愧怍",
      "title": "全栈 typescripter / 学生",
      "url": "https://github.com/kuizuo",
      "imageURL": "/img/logo.webp",
      "key": "kuizuo"
    }
  ],
  "frontMatter": {
    "slug": "question-man",
    "title": "题小侠",
    "date": "2022-04-06T00:00:00.000Z",
    "authors": "kuizuo",
    "tags": [
      "project",
      "vue",
      "miniprogram"
    ],
    "keywords": [
      "project",
      "vue",
      "miniprogram"
    ],
    "image": "/img/project/question-man.png",
    "draft": true
  },
  "prevItem": {
    "title": "搭建GitLab代码管理仓库",
    "permalink": "/gitlab-code-management-environment"
  },
  "nextItem": {
    "title": "vite+vue3搭建uniapp开发环境",
    "permalink": "/vite-vue3-build-uniapp-environment"
  }
}